stake_api/__init__.py
stake_api/main.py
stake_api-0.0.2.dist-info/METADATA
stake_api-0.0.2.dist-info/WHEEL
stake_api-0.0.2.dist-info/top_level.txt
stake_api-0.0.2.dist-info/RECORD
