Metadata-Version: 2.1
Name: stake-api
Version: 0.0.2
Summary: Stake API
Home-page: https://github.com/stake-player/stake-api
Author: stake player
License: Apache License 2.0
Keywords: stake api undetected tip casino bot discord twitter youtube twitch instagram tiktok facebook reddit google app exchange ticket
Classifier: Development Status :: 3 - Alpha
Classifier: Intended Audience :: Developers
Classifier: License :: OSI Approved :: Apache Software License
Classifier: Programming Language :: Python :: 3.9
Requires-Dist: requests
